dotmapdict/__init__.py
dotmapdict/dottydict.py
dotmapdict-1.0.0.dist-info/LICENSE
dotmapdict-1.0.0.dist-info/METADATA
dotmapdict-1.0.0.dist-info/WHEEL
dotmapdict-1.0.0.dist-info/top_level.txt
dotmapdict-1.0.0.dist-info/RECORD
