Metadata-Version: 2.1
Name: dotmapdict
Version: 1.0.0
Summary: A dictionary that supports dot notation access
Home-page: https://github.com/m-sarabi/dotmapdict
Author: Mohammad Sarabi
Author-email: Mohammad Sarabi <m.sarabi.jkd@gmail.com>
License: MIT License
Project-URL: Homepage, https://github.com/m-sarabi/dotmapdict
Project-URL: Documentation, https://github.com/m-sarabi/dotmapdict
Project-URL: Repository, https://github.com/m-sarabi/dotmapdict
Project-URL: Issues, https://github.com/m-sarabi/dotmapdict/issues
Project-URL: Changelog, https://github.com/m-sarabi/dotmapdict/blob/main/CHANGELOG.MD
Keywords: dictionary,dot notation,access,nested,dot,dict,dotdict
Requires-Python: >=3.8
License-File: LICENSE
